{
    "table": {
        "create_access": "false",
        "alter_access": "false",
        "access": "public",
        "live_feed_enabled": "false",
        "sys_updated_on": "2022-10-10 18:02:11",
        "sys_class_name": "sys_db_object",
        "is_extendable": "false",
        "sys_id": "fc5b401897621110d87839000153af1d",
        "user_role": "550cc01897621110d87839000153af92",
        "create_access_controls": "true",
        "delete_access": "false",
        "sys_updated_by": "admin",
        "sys_class_path": "",
        "sys_created_on": "2022-10-10 18:02:11",
        "caller_access": "",
        "client_scripts_access": "false",
        "extension_model": "",
        "actions_access": "false",
        "sys_name": "State Mapping",
        "sys_scope": "c2853b0497221110d87839000153af42",
        "sys_created_by": "admin",
        "__status": "success",
        "sys_class_code": "",
        "read_access": "true",
        "super_class": "",
        "sys_mod_count": "0",
        "ws_access": "true",
        "label": "State Mapping",
        "update_access": "false",
        "sys_package": "c2853b0497221110d87839000153af42",
        "sys_update_name": "sys_db_object_fc5b401897621110d87839000153af1d",
        "scriptable_table": "false",
        "configuration_access": "false",
        "name": "x_44813_persactivt_state_mapping",
        "number_ref": "",
        "sys_policy": ""
    },
    "columns": [
        {
            "calculation": "(function calculatedFieldValue(current) {\n\n\t\/\/ Add your code here\n\treturn '';  \/\/ return the calculated value\n\n})(current);",
            "dynamic_ref_qual": "",
            "choice_field": "",
            "function_field": "false",
            "sys_updated_on": "2022-10-11 12:53:06",
            "spell_check": "false",
            "reference_cascade_rule": "",
            "reference": "",
            "sys_updated_by": "system",
            "read_only": "false",
            "sys_created_on": "2022-10-10 18:02:11",
            "array_denormalized": "false",
            "element_reference": "false",
            "sys_name": "x_44813_persactivt_state_mapping",
            "reference_key": "",
            "reference_qual_condition": "",
            "xml_view": "false",
            "dependent": "",
            "internal_type": "collection",
            "sys_created_by": "admin",
            "element": "",
            "max_length": "40",
            "__status": "success",
            "use_dependent_field": "false",
            "delete_roles": "",
            "active": "true",
            "choice_table": "",
            "foreign_database": "",
            "sys_update_name": "sys_dictionary_x_44813_persactivt_state_mapping_null",
            "unique": "false",
            "name": "x_44813_persactivt_state_mapping",
            "dependent_on_field": "",
            "dynamic_creation": "false",
            "primary": "false",
            "sys_policy": "",
            "next_element": "",
            "virtual": "false",
            "widget": "",
            "use_dynamic_default": "false",
            "sizeclass": "0",
            "mandatory": "false",
            "sys_class_name": "sys_dictionary",
            "dynamic_default_value": "",
            "sys_id": "dd0c881897621110d87839000153af2c",
            "write_roles": "",
            "array": "false",
            "audit": "false",
            "read_roles": "",
            "sys_scope": "c2853b0497221110d87839000153af42",
            "create_roles": "",
            "dynamic_creation_script": "",
            "defaultsort": "",
            "column_label": "",
            "comments": "",
            "use_reference_qualifier": "simple",
            "display": "false",
            "reference_floats": "false",
            "sys_mod_count": "1",
            "default_value": "",
            "staged": "false",
            "reference_type": "",
            "sys_package": "c2853b0497221110d87839000153af42",
            "attributes": "",
            "choice": "",
            "reference_qual": "",
            "table_reference": "false",
            "text_index": "false",
            "function_definition": ""
        },
        {
            "calculation": "(function calculatedFieldValue(current) {\n\n\t\/\/ Add your code here\n\treturn '';  \/\/ return the calculated value\n\n})(current);",
            "dynamic_ref_qual": "",
            "choice_field": "",
            "function_field": "false",
            "sys_updated_on": "2022-10-10 18:02:11",
            "spell_check": "false",
            "reference_cascade_rule": "",
            "reference": "",
            "sys_updated_by": "admin",
            "read_only": "false",
            "sys_created_on": "2022-10-10 18:02:11",
            "array_denormalized": "false",
            "element_reference": "false",
            "sys_name": "inactive",
            "reference_key": "",
            "reference_qual_condition": "",
            "xml_view": "false",
            "dependent": "",
            "internal_type": "boolean",
            "sys_created_by": "admin",
            "element": "inactive",
            "max_length": "40",
            "__status": "success",
            "use_dependent_field": "false",
            "delete_roles": "",
            "active": "true",
            "choice_table": "",
            "foreign_database": "",
            "sys_update_name": "sys_dictionary_x_44813_persactivt_state_mapping_inactive",
            "unique": "false",
            "name": "x_44813_persactivt_state_mapping",
            "dependent_on_field": "",
            "dynamic_creation": "false",
            "primary": "false",
            "sys_policy": "",
            "next_element": "",
            "virtual": "false",
            "widget": "",
            "use_dynamic_default": "false",
            "sizeclass": "",
            "mandatory": "true",
            "sys_class_name": "sys_dictionary",
            "dynamic_default_value": "",
            "sys_id": "9ebb48d497621110d87839000153af39",
            "write_roles": "",
            "array": "false",
            "audit": "false",
            "read_roles": "",
            "sys_scope": "c2853b0497221110d87839000153af42",
            "create_roles": "",
            "dynamic_creation_script": "",
            "defaultsort": "",
            "column_label": "inactive",
            "comments": "",
            "use_reference_qualifier": "simple",
            "display": "false",
            "reference_floats": "false",
            "sys_mod_count": "0",
            "default_value": "false",
            "staged": "false",
            "reference_type": "",
            "sys_package": "c2853b0497221110d87839000153af42",
            "attributes": "",
            "choice": "",
            "reference_qual": "",
            "table_reference": "false",
            "text_index": "false",
            "function_definition": ""
        },
        {
            "calculation": "(function calculatedFieldValue(current) {\n\n\t\/\/ Add your code here\n\treturn '';  \/\/ return the calculated value\n\n})(current);",
            "dynamic_ref_qual": "",
            "choice_field": "",
            "function_field": "false",
            "sys_updated_on": "2022-10-10 18:02:11",
            "spell_check": "false",
            "reference_cascade_rule": "",
            "reference": "",
            "sys_updated_by": "admin",
            "read_only": "false",
            "sys_created_on": "2022-10-10 18:02:11",
            "array_denormalized": "false",
            "element_reference": "false",
            "sys_name": "mapped",
            "reference_key": "",
            "reference_qual_condition": "",
            "xml_view": "false",
            "dependent": "",
            "internal_type": "integer",
            "sys_created_by": "admin",
            "element": "mapped_value",
            "max_length": "40",
            "__status": "success",
            "use_dependent_field": "false",
            "delete_roles": "",
            "active": "true",
            "choice_table": "",
            "foreign_database": "",
            "sys_update_name": "sys_dictionary_x_44813_persactivt_state_mapping_mapped_value",
            "unique": "false",
            "name": "x_44813_persactivt_state_mapping",
            "dependent_on_field": "",
            "dynamic_creation": "false",
            "primary": "false",
            "sys_policy": "",
            "next_element": "",
            "virtual": "false",
            "widget": "",
            "use_dynamic_default": "false",
            "sizeclass": "",
            "mandatory": "true",
            "sys_class_name": "sys_dictionary",
            "dynamic_default_value": "",
            "sys_id": "00abc4d497621110d87839000153afc7",
            "write_roles": "",
            "array": "false",
            "audit": "false",
            "read_roles": "",
            "sys_scope": "c2853b0497221110d87839000153af42",
            "create_roles": "",
            "dynamic_creation_script": "",
            "defaultsort": "",
            "column_label": "mapped",
            "comments": "",
            "use_reference_qualifier": "simple",
            "display": "false",
            "reference_floats": "false",
            "sys_mod_count": "0",
            "default_value": "",
            "staged": "false",
            "reference_type": "",
            "sys_package": "c2853b0497221110d87839000153af42",
            "attributes": "",
            "choice": "",
            "reference_qual": "",
            "table_reference": "false",
            "text_index": "false",
            "function_definition": ""
        },
        {
            "calculation": "(function calculatedFieldValue(current) {\n\n\t\/\/ Add your code here\n\treturn '';  \/\/ return the calculated value\n\n})(current);",
            "dynamic_ref_qual": "",
            "choice_field": "",
            "function_field": "false",
            "sys_updated_on": "2022-10-10 18:02:11",
            "spell_check": "false",
            "reference_cascade_rule": "",
            "reference": "",
            "sys_updated_by": "admin",
            "read_only": "false",
            "sys_created_on": "2022-10-10 18:02:11",
            "array_denormalized": "false",
            "element_reference": "false",
            "sys_name": "source",
            "reference_key": "",
            "reference_qual_condition": "",
            "xml_view": "false",
            "dependent": "",
            "internal_type": "integer",
            "sys_created_by": "admin",
            "element": "source_value",
            "max_length": "40",
            "__status": "success",
            "use_dependent_field": "false",
            "delete_roles": "",
            "active": "true",
            "choice_table": "",
            "foreign_database": "",
            "sys_update_name": "sys_dictionary_x_44813_persactivt_state_mapping_source_value",
            "unique": "false",
            "name": "x_44813_persactivt_state_mapping",
            "dependent_on_field": "",
            "dynamic_creation": "false",
            "primary": "false",
            "sys_policy": "",
            "next_element": "",
            "virtual": "false",
            "widget": "",
            "use_dynamic_default": "false",
            "sizeclass": "",
            "mandatory": "true",
            "sys_class_name": "sys_dictionary",
            "dynamic_default_value": "",
            "sys_id": "737b48d497621110d87839000153af38",
            "write_roles": "",
            "array": "false",
            "audit": "false",
            "read_roles": "",
            "sys_scope": "c2853b0497221110d87839000153af42",
            "create_roles": "",
            "dynamic_creation_script": "",
            "defaultsort": "",
            "column_label": "source",
            "comments": "",
            "use_reference_qualifier": "simple",
            "display": "false",
            "reference_floats": "false",
            "sys_mod_count": "0",
            "default_value": "",
            "staged": "false",
            "reference_type": "",
            "sys_package": "c2853b0497221110d87839000153af42",
            "attributes": "",
            "choice": "",
            "reference_qual": "",
            "table_reference": "false",
            "text_index": "false",
            "function_definition": ""
        },
        {
            "calculation": "",
            "dynamic_ref_qual": "",
            "choice_field": "",
            "function_field": "false",
            "sys_updated_on": "2022-10-10 18:02:12",
            "spell_check": "false",
            "reference_cascade_rule": "",
            "reference": "",
            "sys_updated_by": "admin",
            "read_only": "false",
            "sys_created_on": "2022-10-10 18:02:12",
            "array_denormalized": "false",
            "element_reference": "false",
            "sys_name": "",
            "reference_key": "",
            "reference_qual_condition": "",
            "xml_view": "false",
            "dependent": "",
            "internal_type": "string",
            "sys_created_by": "admin",
            "element": "sys_created_by",
            "max_length": "40",
            "__status": "success",
            "use_dependent_field": "false",
            "delete_roles": "",
            "active": "true",
            "choice_table": "",
            "foreign_database": "",
            "sys_update_name": "",
            "unique": "false",
            "name": "x_44813_persactivt_state_mapping",
            "dependent_on_field": "",
            "dynamic_creation": "false",
            "primary": "false",
            "sys_policy": "",
            "next_element": "",
            "virtual": "false",
            "widget": "",
            "use_dynamic_default": "false",
            "sizeclass": "",
            "mandatory": "false",
            "sys_class_name": "sys_dictionary",
            "dynamic_default_value": "",
            "sys_id": "e50c881897621110d87839000153af3e",
            "write_roles": "",
            "array": "false",
            "audit": "false",
            "read_roles": "",
            "sys_scope": "",
            "create_roles": "",
            "dynamic_creation_script": "",
            "defaultsort": "",
            "column_label": "Created by",
            "comments": "",
            "use_reference_qualifier": "simple",
            "display": "false",
            "reference_floats": "false",
            "sys_mod_count": "0",
            "default_value": "",
            "staged": "false",
            "reference_type": "",
            "sys_package": "",
            "attributes": "",
            "choice": "0",
            "reference_qual": "",
            "table_reference": "false",
            "text_index": "false",
            "function_definition": ""
        },
        {
            "calculation": "",
            "dynamic_ref_qual": "",
            "choice_field": "",
            "function_field": "false",
            "sys_updated_on": "2022-10-10 18:02:12",
            "spell_check": "false",
            "reference_cascade_rule": "",
            "reference": "",
            "sys_updated_by": "admin",
            "read_only": "false",
            "sys_created_on": "2022-10-10 18:02:12",
            "array_denormalized": "false",
            "element_reference": "false",
            "sys_name": "",
            "reference_key": "",
            "reference_qual_condition": "",
            "xml_view": "false",
            "dependent": "",
            "internal_type": "glide_date_time",
            "sys_created_by": "admin",
            "element": "sys_created_on",
            "max_length": "40",
            "__status": "success",
            "use_dependent_field": "false",
            "delete_roles": "",
            "active": "true",
            "choice_table": "",
            "foreign_database": "",
            "sys_update_name": "",
            "unique": "false",
            "name": "x_44813_persactivt_state_mapping",
            "dependent_on_field": "",
            "dynamic_creation": "false",
            "primary": "false",
            "sys_policy": "",
            "next_element": "",
            "virtual": "false",
            "widget": "",
            "use_dynamic_default": "false",
            "sizeclass": "",
            "mandatory": "false",
            "sys_class_name": "sys_dictionary",
            "dynamic_default_value": "",
            "sys_id": "a90c881897621110d87839000153af3f",
            "write_roles": "",
            "array": "false",
            "audit": "false",
            "read_roles": "",
            "sys_scope": "",
            "create_roles": "",
            "dynamic_creation_script": "",
            "defaultsort": "",
            "column_label": "Created",
            "comments": "",
            "use_reference_qualifier": "simple",
            "display": "false",
            "reference_floats": "false",
            "sys_mod_count": "0",
            "default_value": "",
            "staged": "false",
            "reference_type": "",
            "sys_package": "",
            "attributes": "",
            "choice": "0",
            "reference_qual": "",
            "table_reference": "false",
            "text_index": "false",
            "function_definition": ""
        },
        {
            "calculation": "",
            "dynamic_ref_qual": "",
            "choice_field": "",
            "function_field": "false",
            "sys_updated_on": "2022-10-10 18:02:12",
            "spell_check": "false",
            "reference_cascade_rule": "",
            "reference": "",
            "sys_updated_by": "admin",
            "read_only": "false",
            "sys_created_on": "2022-10-10 18:02:12",
            "array_denormalized": "false",
            "element_reference": "false",
            "sys_name": "",
            "reference_key": "",
            "reference_qual_condition": "",
            "xml_view": "false",
            "dependent": "",
            "internal_type": "GUID",
            "sys_created_by": "admin",
            "element": "sys_id",
            "max_length": "32",
            "__status": "success",
            "use_dependent_field": "false",
            "delete_roles": "",
            "active": "true",
            "choice_table": "",
            "foreign_database": "",
            "sys_update_name": "",
            "unique": "false",
            "name": "x_44813_persactivt_state_mapping",
            "dependent_on_field": "",
            "dynamic_creation": "false",
            "primary": "true",
            "sys_policy": "",
            "next_element": "",
            "virtual": "false",
            "widget": "",
            "use_dynamic_default": "false",
            "sizeclass": "",
            "mandatory": "false",
            "sys_class_name": "sys_dictionary",
            "dynamic_default_value": "",
            "sys_id": "ad0c881897621110d87839000153af3a",
            "write_roles": "",
            "array": "false",
            "audit": "false",
            "read_roles": "",
            "sys_scope": "",
            "create_roles": "",
            "dynamic_creation_script": "",
            "defaultsort": "",
            "column_label": "Sys ID",
            "comments": "",
            "use_reference_qualifier": "simple",
            "display": "false",
            "reference_floats": "false",
            "sys_mod_count": "0",
            "default_value": "",
            "staged": "false",
            "reference_type": "",
            "sys_package": "",
            "attributes": "",
            "choice": "0",
            "reference_qual": "",
            "table_reference": "false",
            "text_index": "false",
            "function_definition": ""
        },
        {
            "calculation": "",
            "dynamic_ref_qual": "",
            "choice_field": "",
            "function_field": "false",
            "sys_updated_on": "2022-10-10 18:02:12",
            "spell_check": "false",
            "reference_cascade_rule": "",
            "reference": "",
            "sys_updated_by": "admin",
            "read_only": "false",
            "sys_created_on": "2022-10-10 18:02:12",
            "array_denormalized": "false",
            "element_reference": "false",
            "sys_name": "",
            "reference_key": "",
            "reference_qual_condition": "",
            "xml_view": "false",
            "dependent": "",
            "internal_type": "integer",
            "sys_created_by": "admin",
            "element": "sys_mod_count",
            "max_length": "40",
            "__status": "success",
            "use_dependent_field": "false",
            "delete_roles": "",
            "active": "true",
            "choice_table": "",
            "foreign_database": "",
            "sys_update_name": "",
            "unique": "false",
            "name": "x_44813_persactivt_state_mapping",
            "dependent_on_field": "",
            "dynamic_creation": "false",
            "primary": "false",
            "sys_policy": "",
            "next_element": "",
            "virtual": "false",
            "widget": "",
            "use_dynamic_default": "false",
            "sizeclass": "",
            "mandatory": "false",
            "sys_class_name": "sys_dictionary",
            "dynamic_default_value": "",
            "sys_id": "6d0c881897621110d87839000153af40",
            "write_roles": "",
            "array": "false",
            "audit": "false",
            "read_roles": "",
            "sys_scope": "",
            "create_roles": "",
            "dynamic_creation_script": "",
            "defaultsort": "",
            "column_label": "Updates",
            "comments": "",
            "use_reference_qualifier": "simple",
            "display": "false",
            "reference_floats": "false",
            "sys_mod_count": "0",
            "default_value": "",
            "staged": "false",
            "reference_type": "",
            "sys_package": "",
            "attributes": "",
            "choice": "0",
            "reference_qual": "",
            "table_reference": "false",
            "text_index": "false",
            "function_definition": ""
        },
        {
            "calculation": "",
            "dynamic_ref_qual": "",
            "choice_field": "",
            "function_field": "false",
            "sys_updated_on": "2022-10-10 18:02:12",
            "spell_check": "false",
            "reference_cascade_rule": "",
            "reference": "",
            "sys_updated_by": "admin",
            "read_only": "false",
            "sys_created_on": "2022-10-10 18:02:12",
            "array_denormalized": "false",
            "element_reference": "false",
            "sys_name": "",
            "reference_key": "",
            "reference_qual_condition": "",
            "xml_view": "false",
            "dependent": "",
            "internal_type": "string",
            "sys_created_by": "admin",
            "element": "sys_updated_by",
            "max_length": "40",
            "__status": "success",
            "use_dependent_field": "false",
            "delete_roles": "",
            "active": "true",
            "choice_table": "",
            "foreign_database": "",
            "sys_update_name": "",
            "unique": "false",
            "name": "x_44813_persactivt_state_mapping",
            "dependent_on_field": "",
            "dynamic_creation": "false",
            "primary": "false",
            "sys_policy": "",
            "next_element": "",
            "virtual": "false",
            "widget": "",
            "use_dynamic_default": "false",
            "sizeclass": "",
            "mandatory": "false",
            "sys_class_name": "sys_dictionary",
            "dynamic_default_value": "",
            "sys_id": "610c881897621110d87839000153af3c",
            "write_roles": "",
            "array": "false",
            "audit": "false",
            "read_roles": "",
            "sys_scope": "",
            "create_roles": "",
            "dynamic_creation_script": "",
            "defaultsort": "",
            "column_label": "Updated by",
            "comments": "",
            "use_reference_qualifier": "simple",
            "display": "false",
            "reference_floats": "false",
            "sys_mod_count": "0",
            "default_value": "",
            "staged": "false",
            "reference_type": "",
            "sys_package": "",
            "attributes": "",
            "choice": "0",
            "reference_qual": "",
            "table_reference": "false",
            "text_index": "false",
            "function_definition": ""
        },
        {
            "calculation": "",
            "dynamic_ref_qual": "",
            "choice_field": "",
            "function_field": "false",
            "sys_updated_on": "2022-10-10 18:02:12",
            "spell_check": "false",
            "reference_cascade_rule": "",
            "reference": "",
            "sys_updated_by": "admin",
            "read_only": "false",
            "sys_created_on": "2022-10-10 18:02:12",
            "array_denormalized": "false",
            "element_reference": "false",
            "sys_name": "",
            "reference_key": "",
            "reference_qual_condition": "",
            "xml_view": "false",
            "dependent": "",
            "internal_type": "glide_date_time",
            "sys_created_by": "admin",
            "element": "sys_updated_on",
            "max_length": "40",
            "__status": "success",
            "use_dependent_field": "false",
            "delete_roles": "",
            "active": "true",
            "choice_table": "",
            "foreign_database": "",
            "sys_update_name": "",
            "unique": "false",
            "name": "x_44813_persactivt_state_mapping",
            "dependent_on_field": "",
            "dynamic_creation": "false",
            "primary": "false",
            "sys_policy": "",
            "next_element": "",
            "virtual": "false",
            "widget": "",
            "use_dynamic_default": "false",
            "sizeclass": "",
            "mandatory": "false",
            "sys_class_name": "sys_dictionary",
            "dynamic_default_value": "",
            "sys_id": "250c881897621110d87839000153af3d",
            "write_roles": "",
            "array": "false",
            "audit": "false",
            "read_roles": "",
            "sys_scope": "",
            "create_roles": "",
            "dynamic_creation_script": "",
            "defaultsort": "",
            "column_label": "Updated",
            "comments": "",
            "use_reference_qualifier": "simple",
            "display": "false",
            "reference_floats": "false",
            "sys_mod_count": "0",
            "default_value": "",
            "staged": "false",
            "reference_type": "",
            "sys_package": "",
            "attributes": "",
            "choice": "0",
            "reference_qual": "",
            "table_reference": "false",
            "text_index": "false",
            "function_definition": ""
        },
        {
            "calculation": "(function calculatedFieldValue(current) {\n\n\t\/\/ Add your code here\n\treturn '';  \/\/ return the calculated value\n\n})(current);",
            "dynamic_ref_qual": "",
            "choice_field": "",
            "function_field": "false",
            "sys_updated_on": "2022-10-10 18:02:11",
            "spell_check": "false",
            "reference_cascade_rule": "",
            "reference": "",
            "sys_updated_by": "admin",
            "read_only": "false",
            "sys_created_on": "2022-10-10 18:02:11",
            "array_denormalized": "false",
            "element_reference": "false",
            "sys_name": "table",
            "reference_key": "",
            "reference_qual_condition": "",
            "xml_view": "false",
            "dependent": "",
            "internal_type": "table_name",
            "sys_created_by": "admin",
            "element": "table",
            "max_length": "80",
            "__status": "success",
            "use_dependent_field": "false",
            "delete_roles": "",
            "active": "true",
            "choice_table": "",
            "foreign_database": "",
            "sys_update_name": "sys_dictionary_x_44813_persactivt_state_mapping_table",
            "unique": "false",
            "name": "x_44813_persactivt_state_mapping",
            "dependent_on_field": "",
            "dynamic_creation": "false",
            "primary": "false",
            "sys_policy": "",
            "next_element": "",
            "virtual": "false",
            "widget": "",
            "use_dynamic_default": "false",
            "sizeclass": "",
            "mandatory": "true",
            "sys_class_name": "sys_dictionary",
            "dynamic_default_value": "",
            "sys_id": "c95bccd497621110d87839000153afe8",
            "write_roles": "",
            "array": "false",
            "audit": "false",
            "read_roles": "",
            "sys_scope": "c2853b0497221110d87839000153af42",
            "create_roles": "",
            "dynamic_creation_script": "",
            "defaultsort": "",
            "column_label": "table",
            "comments": "",
            "use_reference_qualifier": "simple",
            "display": "false",
            "reference_floats": "false",
            "sys_mod_count": "0",
            "default_value": "",
            "staged": "false",
            "reference_type": "",
            "sys_package": "c2853b0497221110d87839000153af42",
            "attributes": "",
            "choice": "",
            "reference_qual": "",
            "table_reference": "false",
            "text_index": "false",
            "function_definition": ""
        }
    ]
}
